edge_mdt/__init__.py
edge_mdt_nightly-1.1.0.dist-info/licenses/LICENSE.md
edge_mdt_nightly-1.1.0.dist-info/METADATA
edge_mdt_nightly-1.1.0.dist-info/WHEEL
edge_mdt_nightly-1.1.0.dist-info/top_level.txt
edge_mdt_nightly-1.1.0.dist-info/RECORD
