Metadata-Version: 2.4
Name: edge-mdt-nightly
Version: 1.1.0
Summary: Edge AI Model Development Toolkit
License: Apache-2.0
Classifier: Programming Language :: Python :: 3
Classifier: Operating System :: OS Independent
Classifier: Topic :: Scientific/Engineering :: Artificial Intelligence
Requires-Python: >=3.9
License-File: LICENSE.md
Requires-Dist: model-compression-toolkit~=2.3.0
Requires-Dist: edge-mdt-tpc~=1.1.0
Requires-Dist: imx500-converter~=3.16.1
Requires-Dist: sony-custom-layers~=0.3.0
Provides-Extra: pt
Requires-Dist: imx500-converter[pt]~=3.16.1; extra == "pt"
Provides-Extra: tf
Requires-Dist: imx500-converter[tf]~=3.16.1; extra == "tf"
Dynamic: classifier
Dynamic: description
Dynamic: description-content-type
Dynamic: license
Dynamic: license-file
Dynamic: provides-extra
Dynamic: requires-dist
Dynamic: requires-python
Dynamic: summary
